bdpycmd/__init__.py
bdpycmd/pycmd.py
bdpycmd/cmd/__init__.py
bdpycmd/cmd/camp/__init__.py
bdpycmd/cmd/camp/assistant.py
bdpycmd/cmd/factory/__init__.py
bdpycmd/cmd/factory/base.py
bdpycmd/cmd/factory/dacmd.py
bdpycmd/cmd/factory/dafunc.py
bdpycmd-1.3.31.dist-info/METADATA
bdpycmd-1.3.31.dist-info/WHEEL
bdpycmd-1.3.31.dist-info/top_level.txt
bdpycmd-1.3.31.dist-info/RECORD
