Metadata-Version: 2.1
Name: bdpycmd
Version: 1.3.31
Summary: Run Python`s file as command line
Home-page: https://github.com/biandoucheng/bd-py-cmd
Author: biandoucheng
Author-email: biandoucheng@outlook.com
Project-URL: Bug Tracker, https://github.com/biandoucheng/bd-py-cmd/issues
Project-URL: Use Example, https://github.com/biandoucheng/open-example/tree/main/bdpycmd-example
Classifier: Programming Language :: Python :: 3.5
Classifier: License :: OSI Approved :: Apache Software License
Classifier: Operating System :: OS Independent
Classifier: Development Status :: 5 - Production/Stable
Requires-Python: >=3.5
